src/__init__.py
src/main.py
mdm2ckan-0.0.0.dist-info/LICENSE
mdm2ckan-0.0.0.dist-info/METADATA
mdm2ckan-0.0.0.dist-info/WHEEL
mdm2ckan-0.0.0.dist-info/top_level.txt
mdm2ckan-0.0.0.dist-info/RECORD
