Metadata-Version: 2.1
Name: mdm2ckan
Version: 0.0.0
Home-page: https://github.com/enprava/MDM2CKAN
Author: enprava
Author-email: enprava <epradavazquez@gmail.com>
License: Copyright (c) 2018 The Python Packaging Authority        
Project-URL: Homepage, https://github.com/enprava/MDM2CKAN/
Project-URL: Bug Tracker, https://github.com/enprava/MDM2CKAN/issues
Classifier: Programming Language :: Python :: 3
Classifier: License :: OSI Approved :: MIT License
Classifier: Operating System :: OS Independent
Requires-Python: >=3.10
License-File: LICENSE
